cli_contacts/__init__.py
cli_contacts/cli_contacts.py
cli_contacts/models.py
cli_contacts-0.6.1.dist-info/entry_points.txt
cli_contacts-0.6.1.dist-info/WHEEL
cli_contacts-0.6.1.dist-info/METADATA
cli_contacts-0.6.1.dist-info/RECORD
